barril/__init__.py
barril/conftest.py
barril/py.typed
barril/_util/__init__.py
barril/_util/types_.py
barril/_util/_tests/__init__.py
barril/_util/_tests/test_types.py
barril/basic/__init__.py
barril/basic/format_float/__init__.py
barril/basic/format_float/_tests/__init__.py
barril/basic/format_float/_tests/test_format_float.py
barril/basic/fraction/__init__.py
barril/basic/fraction/_fraction.py
barril/basic/fraction/_fraction_value.py
barril/basic/fraction/_tests/__init__.py
barril/basic/fraction/_tests/test_fraction.py
barril/basic/fraction/_tests/test_fraction_value.py
barril/curve/__init__.py
barril/curve/curve.py
barril/curve/curve_interface.py
barril/curve/_tests/__init__.py
barril/curve/_tests/test_curve.py
barril/units/__init__.py
barril/units/_abstractvaluewithquantity.py
barril/units/_array.py
barril/units/_fixedarray.py
barril/units/_fraction_scalar.py
barril/units/_quantity.py
barril/units/_scalar.py
barril/units/_unit_constants.py
barril/units/_value_generator.py
barril/units/exceptions.py
barril/units/interfaces.py
barril/units/posc.py
barril/units/unit_database.py
barril/units/unit_rich_text_representations.py
barril/units/unit_system.py
barril/units/unit_system_interface.py
barril/units/unit_system_manager.py
barril/units/_tests/__init__.py
barril/units/_tests/test_array.py
barril/units/_tests/test_derived_quantities.py
barril/units/_tests/test_empty_scalar.py
barril/units/_tests/test_fixedarray.py
barril/units/_tests/test_fraction_scalar.py
barril/units/_tests/test_legacy_unit.py
barril/units/_tests/test_operations.py
barril/units/_tests/test_posc.py
barril/units/_tests/test_posc2.py
barril/units/_tests/test_posc_additional_units.py
barril/units/_tests/test_quantity.py
barril/units/_tests/test_read_only_quantity.py
barril/units/_tests/test_scalar.py
barril/units/_tests/test_scalar_and_quantity.py
barril/units/_tests/test_scalar_refactor.py
barril/units/_tests/test_unit_database.py
barril/units/_tests/test_unit_rich_text_representations.py
barril-2.2.1.dist-info/licenses/LICENSE
barril-2.2.1.dist-info/METADATA
barril-2.2.1.dist-info/WHEEL
barril-2.2.1.dist-info/top_level.txt
barril-2.2.1.dist-info/RECORD
