Metadata-Version: 2.4
Name: barril
Version: 2.2.1
Summary: Python package to manage units for physical quantities
Home-page: https://github.com/ESSS/barril
Author: ESSS
Author-email: foss@esss.co
License: MIT license
Keywords: barril
Classifier: Development Status :: 5 - Production/Stable
Classifier: Intended Audience :: Developers
Classifier: License :: OSI Approved :: MIT License
Classifier: Programming Language :: Python :: 3.9
Classifier: Programming Language :: Python :: 3.10
Classifier: Programming Language :: Python :: 3.11
Classifier: Programming Language :: Python :: 3.12
Classifier: Programming Language :: Python :: 3.13
Requires-Python: >=3.9
License-File: LICENSE
Requires-Dist: attrs>=18.1.0
Requires-Dist: numpy>=1.11.0
Requires-Dist: oop-ext>=1.1
Requires-Dist: typing_extensions
Provides-Extra: testing
Requires-Dist: codecov; extra == "testing"
Requires-Dist: data-science-types; extra == "testing"
Requires-Dist: mypy; extra == "testing"
Requires-Dist: pre-commit; extra == "testing"
Requires-Dist: pytest; extra == "testing"
Requires-Dist: pytest-cov; extra == "testing"
Requires-Dist: pytest-mock; extra == "testing"
Requires-Dist: tox; extra == "testing"
Dynamic: author
Dynamic: author-email
Dynamic: classifier
Dynamic: description
Dynamic: description-content-type
Dynamic: home-page
Dynamic: keywords
Dynamic: license
Dynamic: license-file
Dynamic: provides-extra
Dynamic: requires-dist
Dynamic: requires-python
Dynamic: summary
